orthofinder_tools/__init__.py
orthofinder_tools/annotate_orthogroups.py
orthofinder_tools/orthofinder_plots.py
orthofinder_tools/utils.py
orthofinder_tools-0.0.4.dist-info/WHEEL
orthofinder_tools-0.0.4.dist-info/entry_points.txt
orthofinder_tools-0.0.4.dist-info/METADATA
orthofinder_tools-0.0.4.dist-info/RECORD
