Metadata-Version: 2.3
Name: orthofinder-tools
Version: 0.0.4
Summary: Annotate orthogenes and create Roary-like plots
Author: Thomas Roder
Author-email: Thomas Roder <roder.thomas@gmail.com>
License: MIT
Classifier: Development Status :: 4 - Beta
Classifier: Intended Audience :: Science/Research
Classifier: License :: OSI Approved :: MIT License
Classifier: Operating System :: POSIX :: Linux
Classifier: Programming Language :: Python :: 3.14
Requires-Dist: numpy
Requires-Dist: pandas
Requires-Dist: biopython
Requires-Dist: fire
Requires-Dist: matplotlib
Requires-Dist: seaborn
Requires-Python: >=3.10
Project-URL: Repository, https://github.com/MrTomRod/orthofinder-tools/
